Metadata-Version: 2.1
Name: Chordix
Version: 0.0.11
Summary: Chordix uses harmony theories to analyse chords, chord progressions and midi music segments.
Home-page: https://github.com/JasonLee-p/Chordix
Author: Jason Lee
Author-email: 2593292614@qq.com
Classifier: Programming Language :: Python :: 3
Classifier: License :: OSI Approved :: Mozilla Public License 2.0 (MPL 2.0)
Classifier: Operating System :: OS Independent
License-File: LICENSE
Requires-Dist: numpy==1.21.2
